irispie/__init__.py
irispie/_banners.py
irispie/attributes.py
irispie/contexts.py
irispie/equations.py
irispie/file_io.py
irispie/frames.py
irispie/iter_printers.py
irispie/keywords.py
irispie/makers.py
irispie/namings.py
irispie/portables.py
irispie/progress_bars.py
irispie/pyrightconfig.json
irispie/quantities.py
irispie/sources.py
irispie/aldi/__init__.py
irispie/aldi/adaptations.py
irispie/aldi/differentiators.py
irispie/aldi/finite_differentiators.py
irispie/aldi/invariators.py
irispie/aldi/maps.py
irispie/dataslates/__init__.py
irispie/dataslates/_invariants.py
irispie/dataslates/_slatables.py
irispie/dataslates/_variants.py
irispie/dataslates/main.py
irispie/equators/__init__.py
irispie/equators/plain.py
irispie/evaluators/__init__.py
irispie/evaluators/base.py
irispie/explanatories/__init__.py
irispie/explanatories/_transforms.py
irispie/explanatories/main.py
irispie/fords/__init__.py
irispie/fords/covariances.py
irispie/fords/descriptors.py
irispie/fords/initializers.py
irispie/fords/kalmans.py
irispie/fords/least_squares.py
irispie/fords/shock_simulators.py
irispie/fords/simulators.py
irispie/fords/solutions.py
irispie/fords/std_simulators.py
irispie/fords/steadiers.py
irispie/fords/systems.py
irispie/fords/terminators.py
irispie/incidences/_dulmage_mendelsohn.py
irispie/incidences/blazer.py
irispie/incidences/cells.py
irispie/incidences/main.py
irispie/jacobians/__init__.py
irispie/jacobians/base.py
irispie/parsers/__init__.py
irispie/parsers/_lists.py
irispie/parsers/_pseudofunctions.py
irispie/parsers/_shifts.py
irispie/parsers/_substitutions.py
irispie/parsers/common.py
irispie/parsers/models.py
irispie/parsers/preparser.py
irispie/period_by_period/_equators.py
irispie/period_by_period/_evaluators.py
irispie/period_by_period/_iter_printers.py
irispie/period_by_period/_jacobians.py
irispie/period_by_period/simulators.py
irispie/plans/__init__.py
irispie/plans/_indexes.py
irispie/plans/_pretty.py
irispie/plans/_registers.py
irispie_ce-0.77.1.dist-info/METADATA
irispie_ce-0.77.1.dist-info/WHEEL
irispie_ce-0.77.1.dist-info/licenses/LICENSE
irispie_ce-0.77.1.dist-info/licenses/NOTICE
irispie_ce-0.77.1.dist-info/RECORD
