Metadata-Version: 2.4
Name: irispie-ce
Version: 0.77.1
Summary: Macroeconomic modeling package
Project-URL: Homepage, https://github.com/iris-solutions-team/irispie-ce
Project-URL: Documentation, https://iris-solutions-team.github.io/irispie-pages
Project-URL: Bug Tracker, https://github.com/iris-solutions-team/irispie-ce/issues
Author-email: Jaromir Benes <jaromir.benes@gmail.com>
License: OGResearch Community License 1.0
License-File: LICENSE
License-File: NOTICE
Keywords: dsge,economics,forecasting,macroeconomics,modeling,simulation
Classifier: License :: Other/Proprietary License
Classifier: Operating System :: OS Independent
Classifier: Programming Language :: Python :: 3
Requires-Python: >=3.11
Requires-Dist: daqp>=0.6.0
Requires-Dist: datapie>=0.3.2
Requires-Dist: dill>=0.3.8
Requires-Dist: documark>=0.4.0
Requires-Dist: jinja2>=3.1.4
Requires-Dist: kaleido>=1.1.0
Requires-Dist: neqs>=0.9.0
Requires-Dist: numpy>=2.1
Requires-Dist: pandas>=2.1.2
Requires-Dist: parsimonious>=0.10
Requires-Dist: plotly>=6.3
Requires-Dist: prettytable>=3.10
Requires-Dist: python-dateutil>=2.9.0
Requires-Dist: scipy>=1.14.1
